jupyter_weav_app_one/__init__.py
jupyter_weav_app_one/_version.py
jupyter_weav_app_one/labextension/package.json
jupyter_weav_app_one/labextension/static/534.37c84a40d8736cb22391.js
jupyter_weav_app_one/labextension/static/778.ebe95c97983bf43590b7.js
jupyter_weav_app_one/labextension/static/remoteEntry.111cd303c325dc170eb2.js
jupyter_weav_app_one/labextension/static/style.js
jupyter_weav_app_one-0.1.0.data/data/share/jupyter/labextensions/jupyter_weav_app_one/install.json
jupyter_weav_app_one-0.1.0.data/data/share/jupyter/labextensions/jupyter_weav_app_one/package.json
jupyter_weav_app_one-0.1.0.data/data/share/jupyter/labextensions/jupyter_weav_app_one/static/534.37c84a40d8736cb22391.js
jupyter_weav_app_one-0.1.0.data/data/share/jupyter/labextensions/jupyter_weav_app_one/static/778.ebe95c97983bf43590b7.js
jupyter_weav_app_one-0.1.0.data/data/share/jupyter/labextensions/jupyter_weav_app_one/static/remoteEntry.111cd303c325dc170eb2.js
jupyter_weav_app_one-0.1.0.data/data/share/jupyter/labextensions/jupyter_weav_app_one/static/style.js
jupyter_weav_app_one-0.1.0.dist-info/LICENSE
jupyter_weav_app_one-0.1.0.dist-info/METADATA
jupyter_weav_app_one-0.1.0.dist-info/WHEEL
jupyter_weav_app_one-0.1.0.dist-info/top_level.txt
jupyter_weav_app_one-0.1.0.dist-info/RECORD
